MANIFEST.in
README.txt
setup.py
cms_facetsearch/__init__.py
cms_facetsearch/cms_app.py
cms_facetsearch/forms.py
cms_facetsearch/indexes.py
cms_facetsearch/models.py
cms_facetsearch/search_indexes.py
cms_facetsearch/locale/de/LC_MESSAGES/django.po
cms_facetsearch/locale/fr/LC_MESSAGES/django.po
cms_facetsearch/locale/it/LC_MESSAGES/django.po
cms_facetsearch/locale/nb/LC_MESSAGES/django.mo
cms_facetsearch/locale/nb/LC_MESSAGES/django.po
cms_facetsearch/locale/nn/LC_MESSAGES/django.po
cms_facetsearch/templates/search/base.html
cms_facetsearch/templates/search/cms_search.html
django_cms_facetsearch.egg-info/PKG-INFO
django_cms_facetsearch.egg-info/SOURCES.txt
django_cms_facetsearch.egg-info/dependency_links.txt
django_cms_facetsearch.egg-info/not-zip-safe
django_cms_facetsearch.egg-info/top_level.txt