Metadata-Version: 1.0
Name: django-cms-facetsearch
Version: 0.9.2
Summary: Searching using language facets for django-cms pages and plugins.
Home-page: http://github.com/fivethreeo/django-cms-facetsearch/
Author: Oyvind Saltvik
Author-email: oyvind.saltvik@gmail.com
License: UNKNOWN
Platform: UNKNOWN
